xc_enc/__init__.py
xc_enc/enc.py
xc_enc/config/__init__.py
xc_enc/config/sk.py
xc_enc/util/__init__.py
xc_enc/util/file.py
xc_enc/util/progress.py
xc_enc-1.0.0.dist-info/LICENSE
xc_enc-1.0.0.dist-info/METADATA
xc_enc-1.0.0.dist-info/WHEEL
xc_enc-1.0.0.dist-info/entry_points.txt
xc_enc-1.0.0.dist-info/top_level.txt
xc_enc-1.0.0.dist-info/RECORD
