Metadata-Version: 2.1
Name: xc_enc
Version: 1.0.0
Summary: Encrypt files.
Project-URL: Repository, https://github.com/xcFelix/xc_enc
Requires-Python: >=3.8
License-File: LICENSE
Requires-Dist: cryptography ==42.0.7
Requires-Dist: tomlkit ==0.12.4
